open_source_fpga_environment/Transmisor/src/design/bin_a_7seg.sv
// ============================================================
// Modulo 5.3: Codificacion binario a 7 segmentos
// EL-3307 Diseno Logico - Proyecto Corto I
// ------------------------------------------------------------
// Que es: el subsistema 5.3 del enunciado (codificacion binario
// a 7 segmentos), implementado dentro de la FPGA.
// Que hace: recibe una palabra de 4 bits (datos) y entrega el
// patron de segmentos que hay que prender en el display para
// mostrar ese numero en hexadecimal (0 a F).
//
// Mismo patron que el ejemplo "sevenseg" visto en clase
// (Harris & Harris): always_comb + case.
// seg = {g, f, e, d, c, b, a}, activo en ALTO (display de
// CATODO COMUN: el catodo compartido va a GND, y cada segmento
// a,b,c,d,e,f,g se enciende con un 1 desde la FPGA a traves de
// una resistencia de 330 ohm).
// ============================================================
 
module bin_a_7seg (
    input  logic [3:0] datos,
    output logic [6:0] seg      // {g,f,e,d,c,b,a}, activo en ALTO
);
 
    always_comb
        case (datos)
            // abc_defg (igual notacion que en clase)
            4'h0: seg = 7'b0111111;
            4'h1: seg = 7'b0000110;
            4'h2: seg = 7'b1011011;
            4'h3: seg = 7'b1001111;
            4'h4: seg = 7'b1100110;
            4'h5: seg = 7'b1101101;
            4'h6: seg = 7'b1111101;
            4'h7: seg = 7'b0000111;
            4'h8: seg = 7'b1111111;
            4'h9: seg = 7'b1101111;
            4'hA: seg = 7'b1110111;
            4'hB: seg = 7'b1111100;
            4'hC: seg = 7'b0111001;
            4'hD: seg = 7'b1011110;
            4'hE: seg = 7'b1111001;
            4'hF: seg = 7'b1110001;
            default: seg = 7'b0000000; // requerido
        endcase
 
endmodule

open_source_fpga_environment/Transmisor/src/sim/bin_a_7seg_tb.sv
// ============================================================
// Testbench basico: bin_a_7seg
// EL-3307 Diseno Logico - Proyecto Corto I
// ------------------------------------------------------------
// Que es: banco de pruebas (testbench) del subsistema 5.3.
// Que hace: prueba los 16 valores posibles de "datos" (0 a F) y
// compara la salida "seg" contra el valor que debería salir,
// para confirmar que el decodificador esta bien.
//
// Compilar con:
//   iverilog -Wall -g2012 -o sim_7seg bin_a_7seg.sv bin_a_7seg_tb.sv
//   vvp sim_7seg
// ============================================================
 
`timescale 1ns/1ps
 
module bin_a_7seg_tb;
 
    // Senales que se conectan al modulo que se esta probando (dut)
    logic [3:0] datos;
    logic [6:0] seg;
 
    // Contadores simples para el resumen final
    integer errores;
    integer i;
 
    // Tabla con el valor de "seg" que se espera para cada digito
    logic [6:0] esperado [0:15];
 
    // dut = "device under test", el modulo que estamos probando
    bin_a_7seg dut (
        .datos(datos),
        .seg  (seg)
    );
 
    initial begin
        // Estas dos lineas son las que permiten generar el archivo
        // .vcd que despues abre "make wv" (GTKWave) para ver las
        // formas de onda de las senales.
        $dumpfile("bin_a_7seg_tb.vcd");
        $dumpvars(0, bin_a_7seg_tb);
 
        // Se llena la tabla de valores esperados.
        // Activo en ALTO porque el display es de catodo comun
        // (1 = segmento encendido), por eso ya NO se invierte con ~.
        esperado[0]  = 7'b0111111;
        esperado[1]  = 7'b0000110;
        esperado[2]  = 7'b1011011;
        esperado[3]  = 7'b1001111;
        esperado[4]  = 7'b1100110;
        esperado[5]  = 7'b1101101;
        esperado[6]  = 7'b1111101;
        esperado[7]  = 7'b0000111;
        esperado[8]  = 7'b1111111;
        esperado[9]  = 7'b1101111;
        esperado[10] = 7'b1110111;
        esperado[11] = 7'b1111100;
        esperado[12] = 7'b0111001;
        esperado[13] = 7'b1011110;
        esperado[14] = 7'b1111001;
        esperado[15] = 7'b1110001;
 
        errores = 0;
 
        // Se prueban los 16 digitos, uno por uno
        for (i = 0; i < 16; i = i + 1) begin
            datos = i[3:0];
            #10; // se espera a que la salida se acomode
 
            if (seg !== esperado[i]) begin
                $display("FALLO: datos=%h  seg=%b  esperado=%b", datos, seg, esperado[i]);
                errores = errores + 1;
            end else begin
                $display("OK   : datos=%h  seg=%b", datos, seg);
            end
        end
 
        // Resumen final
        if (errores == 0)
            $display("\n*** TODAS LAS PRUEBAS PASARON ***");
        else
            $display("\n*** %0d PRUEBA(S) FALLARON ***", errores);
 
        $finish;
    end
 
endmodule

open_source_fpga_environment/Transmisor/src/build/bin_a_7seg_tb.vcd
$date
	Wed Sep 23 08:56:12 2026
$end
$version
	Icarus Verilog
$end
$timescale
	1ps
$end
$scope module bin_a_7seg_tb $end
$var wire 7 ! seg [6:0] $end
$var reg 4 " datos [3:0] $end
$var integer 32 # errores [31:0] $end
$var integer 32 $ i [31:0] $end
$scope module dut $end
$var wire 4 % datos [3:0] $end
$var reg 7 & seg [6:0] $end
$upscope $end
$upscope $end
$enddefinitions $end
$comment Show the parameter values. $end
$dumpall
$end
#0
$dumpvars
b111111 &
b0 %
b0 $
b0 #
b0 "
b111111 !
$end
#10000
b110 !
b110 &
b1 "
b1 %
b1 $
#20000
b1011011 !
b1011011 &
b10 "
b10 %
b10 $
#30000
b1001111 !
b1001111 &
b11 "
b11 %
b11 $
#40000
b1100110 !
b1100110 &
b100 "
b100 %
b100 $
#50000
b1101101 !
b1101101 &
b101 "
b101 %
b101 $
#60000
b1111101 !
b1111101 &
b110 "
b110 %
b110 $
#70000
b111 !
b111 &
b111 "
b111 %
b111 $
#80000
b1111111 !
b1111111 &
b1000 "
b1000 %
b1000 $
#90000
b1101111 !
b1101111 &
b1001 "
b1001 %
b1001 $
#100000
b1110111 !
b1110111 &
b1010 "
b1010 %
b1010 $
#110000
b1111100 !
b1111100 &
b1011 "
b1011 %
b1011 $
#120000
b111001 !
b111001 &
b1100 "
b1100 %
b1100 $
#130000
b1011110 !
b1011110 &
b1101 "
b1101 %
b1101 $
#140000
b1111001 !
b1111001 &
b1110 "
b1110 %
b1110 $
#150000
b1110001 !
b1110001 &
b1111 "
b1111 %
b1111 $
#160000
b10000 $
